{"repo": {"timestamp": 1635405366000, "version": 21, "name": "SmartOfficeSchool", "icon": "default-repo-icon.png", "address": "https://raw.githubusercontent.com/smartofficeschool/fdroid/master/fdroid/repo", "description": "Marcelis | Smart Office & School", "mirrors": ["https://localhost/repos/b-zmF1dXbJAxIzRVE-YxuWLbVRvjSDcP/repo/repo", "https://marcelis.be/fdroid/repo", "https://raw.githubusercontent.com/smartofficeschool/fdroid/master/fdroid/repo/repo"]}, "requests": {"install": [], "uninstall": []}, "apps": [{"suggestedVersionCode": "2002718423", "license": "Unknown", "name": "PowerPoint", "added": 1635372803000, "icon": "com.microsoft.office.powerpoint.2002718423.png", "packageName": "com.microsoft.office.powerpoint", "lastUpdated": 1635372823000}], "packages": {"com.microsoft.office.powerpoint": [{"added": 1635372811000, "apkName": "Microsoft_PowerPoint_Slideshows_and_Presentations_v16.0.14527.20162_apkpure.com.apk", "features": ["android.hardware.screen.landscape"], "hash": "13fa866e04638ee78f5681a31e9cd35cda030e91ffbc8a6c837426b60f3c5372", "hashType": "sha256", "minSdkVersion": 26, "nativecode": ["arm64-v8a"], "packageName": "com.microsoft.office.powerpoint", "sig": "78f479347f66a38efdf2402ccf8aaedc", "signer": "b925136f3ea7c0a1951690a1ab313910da81f40994a85342ec622888f1287051", "size": 67205242, "targetSdkVersion": 30, "uses-permission": [["android.permission.WRITE_EXTERNAL_STORAGE", null], ["android.permission.MANAGE_EXTERNAL_STORAGE", null], ["android.permission.RECEIVE_BOOT_COMPLETED", null], ["android.permission.GET_ACCOUNTS", null], ["android.permission.MANAGE_ACCOUNTS", null], ["android.permission.AUTHENTICATE_ACCOUNTS", null], ["android.permission.USE_CREDENTIALS", null], ["android.permission.INTERNET", null], ["android.permission.ACCESS_NETWORK_STATE", null], ["android.permission.ACCESS_WIFI_STATE", null], ["com.android.vending.CHECK_LICENSE", null], ["android.permission.READ_USER_DICTIONARY", null], ["android.permission.WRITE_USER_DICTIONARY", null], ["com.android.launcher.permission.INSTALL_SHORTCUT", null], ["android.permission.VIBRATE", null], ["android.permission.RECORD_AUDIO", null], ["android.permission.MODIFY_AUDIO_SETTINGS", null], ["com.google.android.c2dm.permission.RECEIVE", null], ["com.microsoft.office.powerpoint.permission.C2D_MESSAGE", null], ["android.permission.READ_CONTACTS", null], ["android.permission.SYSTEM_ALERT_WINDOW", null], ["android.permission.GET_PACKAGE_SIZE", null], ["android.permission.CAMERA", null], ["com.android.vending.BILLING", null], ["android.permission.READ_PHONE_STATE", null], ["android.permission.WAKE_LOCK", null], ["android.permission.READ_EXTERNAL_STORAGE", null]], "versionCode": 2002718423, "versionName": "16.0.14527.20162"}, {"added": 1635372823000, "apkName": "powerpoint.apk", "features": ["android.hardware.screen.landscape"], "hash": "13fa866e04638ee78f5681a31e9cd35cda030e91ffbc8a6c837426b60f3c5372", "hashType": "sha256", "minSdkVersion": 26, "nativecode": ["arm64-v8a"], "packageName": "com.microsoft.office.powerpoint", "sig": "78f479347f66a38efdf2402ccf8aaedc", "signer": "b925136f3ea7c0a1951690a1ab313910da81f40994a85342ec622888f1287051", "size": 67205242, "targetSdkVersion": 30, "uses-permission": [["android.permission.WRITE_EXTERNAL_STORAGE", null], ["android.permission.MANAGE_EXTERNAL_STORAGE", null], ["android.permission.RECEIVE_BOOT_COMPLETED", null], ["android.permission.GET_ACCOUNTS", null], ["android.permission.MANAGE_ACCOUNTS", null], ["android.permission.AUTHENTICATE_ACCOUNTS", null], ["android.permission.USE_CREDENTIALS", null], ["android.permission.INTERNET", null], ["android.permission.ACCESS_NETWORK_STATE", null], ["android.permission.ACCESS_WIFI_STATE", null], ["com.android.vending.CHECK_LICENSE", null], ["android.permission.READ_USER_DICTIONARY", null], ["android.permission.WRITE_USER_DICTIONARY", null], ["com.android.launcher.permission.INSTALL_SHORTCUT", null], ["android.permission.VIBRATE", null], ["android.permission.RECORD_AUDIO", null], ["android.permission.MODIFY_AUDIO_SETTINGS", null], ["com.google.android.c2dm.permission.RECEIVE", null], ["com.microsoft.office.powerpoint.permission.C2D_MESSAGE", null], ["android.permission.READ_CONTACTS", null], ["android.permission.SYSTEM_ALERT_WINDOW", null], ["android.permission.GET_PACKAGE_SIZE", null], ["android.permission.CAMERA", null], ["com.android.vending.BILLING", null], ["android.permission.READ_PHONE_STATE", null], ["android.permission.WAKE_LOCK", null], ["android.permission.READ_EXTERNAL_STORAGE", null]], "versionCode": 2002718423, "versionName": "16.0.14527.20162"}]}}